sqlalchemy_paginator/__init__.py
sqlalchemy_paginator/exceptions.py
sqlalchemy_paginator/paginator.py
SQLAlchemy_Paginator-0.2.dist-info/LICENSE.txt
SQLAlchemy_Paginator-0.2.dist-info/METADATA
SQLAlchemy_Paginator-0.2.dist-info/WHEEL
SQLAlchemy_Paginator-0.2.dist-info/top_level.txt
SQLAlchemy_Paginator-0.2.dist-info/RECORD
