Metadata-Version: 2.1
Name: SQLAlchemy-Paginator
Version: 0.2
Summary: Paginator for SQLAlchemy ORM
Home-page: https://github.com/ahmadjavedse/sqlalchemy-paginator.git
Author: Ahmad Javed
Author-email: ahmadjaved.se@gmail.com
License: MIT
Keywords: sqlalchemy pagination paginator paginate sqlalchemy-orm paging slicing sqlalchemy-query
Platform: UNKNOWN
Classifier: Development Status :: 3 - Alpha
Classifier: Intended Audience :: Developers
Classifier: Topic :: Software Development :: Build Tools
Classifier: Topic :: Software Development :: Libraries :: Python Modules
Classifier: Programming Language :: Python :: 2.7
Classifier: Programming Language :: Python :: 3
Classifier: Programming Language :: Python :: 3.8
Classifier: License :: OSI Approved :: MIT License
Classifier: Operating System :: OS Independent
